{
  "type": "forge:ore_shaped",
  "pattern": [
    "AAA",
    "BCB",
    "BDB"
  ],
  "key": {
    "A": {
      "type": "forge:ore_dict",
      "ore": "plankWood",
      "count": 1
    },
    "B": {
      "type": "forge:ore_dict",
      "ore": "cobblestone",
      "count": 1
    },
    "C": {
      "item": "magneticraft:crafting",
      "count": 1,
      "data": 2
    },
    "D": {
      "type": "forge:ore_dict",
      "ore": "dustRedstone",
      "count": 1
    }
  },
  "result": {
    "item": "magneticraft:transposer",
    "count": 1,
    "data": 0
  }
}